{
  "openapi": "3.0.1",
  "info": {
    "title": "BidNow Identity Service API",
    "description": "API documentation for Authentication and Authorization in Identity Service",
    "version": "1.0.0"
  },
  "servers": [
    {
      "url": "http://localhost:8081",
      "description": "Local server"
    }
  ],
  "paths": {
    "/api/v1/auth/register": {
      "post": {
        "tags": ["Auth Controller"],
        "summary": "Register a new user account",
        "requestBody": {
          "content": {
            "application/json": {
              "schema": {
                "$ref": "#/components/schemas/RegisterRequest"
              }
            }
          },
          "required": true
        },
        "responses": {
          "201": {
            "description": "User registered successfully",
            "content": {
              "application/json": {
                "schema": {
                  "$ref": "#/components/schemas/ApiResponseRegisterResponse"
                }
              }
            }
          },
          "400": {
            "description": "Validation error or email already registered",
            "content": {
              "application/json": {
                "schema": {
                  "$ref": "#/components/schemas/ErrorResponse"
                }
              }
            }
          }
        }
      }
    },
    "/api/v1/auth/login": {
      "post": {
        "tags": ["Auth Controller"],
        "summary": "Authenticate user and issue tokens",
        "requestBody": {
          "content": {
            "application/json": {
              "schema": {
                "$ref": "#/components/schemas/LoginRequest"
              }
            }
          },
          "required": true
        },
        "responses": {
          "200": {
            "description": "Login successful",
            "content": {
              "application/json": {
                "schema": {
                  "$ref": "#/components/schemas/ApiResponseLoginResponse"
                }
              }
            }
          },
          "400": {
            "description": "Validation error",
            "content": {
              "application/json": {
                "schema": {
                  "$ref": "#/components/schemas/ErrorResponse"
                }
              }
            }
          },
          "401": {
            "description": "Invalid credentials, account disabled, or account temporarily locked",
            "content": {
              "application/json": {
                "schema": {
                  "$ref": "#/components/schemas/ErrorResponse"
                }
              }
            }
          }
        }
      }
    },
    "/api/v1/auth/refresh": {
      "post": {
        "tags": ["Auth Controller"],
        "summary": "Refresh access token using a valid refresh token",
        "requestBody": {
          "content": {
            "application/json": {
              "schema": {
                "$ref": "#/components/schemas/RefreshTokenRequest"
              }
            }
          },
          "required": true
        },
        "responses": {
          "200": {
            "description": "Token refreshed successfully",
            "content": {
              "application/json": {
                "schema": {
                  "$ref": "#/components/schemas/ApiResponseLoginResponse"
                }
              }
            }
          },
          "401": {
            "description": "Invalid, revoked, or expired refresh token",
            "content": {
              "application/json": {
                "schema": {
                  "$ref": "#/components/schemas/ErrorResponse"
                }
              }
            }
          }
        }
      }
    },
    "/api/v1/auth/logout": {
      "post": {
        "tags": ["Auth Controller"],
        "summary": "Revoke the provided refresh token",
        "requestBody": {
          "content": {
            "application/json": {
              "schema": {
                "$ref": "#/components/schemas/RefreshTokenRequest"
              }
            }
          },
          "required": true
        },
        "responses": {
          "204": {
            "description": "Logged out successfully"
          }
        }
      }
    }
  },
  "components": {
    "schemas": {
      "RegisterRequest": {
        "type": "object",
        "required": ["email", "password"],
        "properties": {
          "email": {
            "type": "string",
            "format": "email"
          },
          "password": {
            "type": "string",
            "minLength": 8
          }
        }
      },
      "LoginRequest": {
        "type": "object",
        "required": ["email", "password"],
        "properties": {
          "email": {
            "type": "string",
            "format": "email"
          },
          "password": {
            "type": "string"
          }
        }
      },
      "RefreshTokenRequest": {
        "type": "object",
        "required": ["refreshToken"],
        "properties": {
          "refreshToken": {
            "type": "string"
          }
        }
      },
      "RegisterResponse": {
        "type": "object",
        "properties": {
          "userId": {
            "type": "string",
            "format": "uuid"
          },
          "email": {
            "type": "string",
            "format": "email"
          },
          "isEmailVerified": {
            "type": "boolean"
          },
          "isActive": {
            "type": "boolean"
          },
          "createdAt": {
            "type": "string",
            "format": "date-time"
          }
        }
      },
      "LoginResponse": {
        "type": "object",
        "properties": {
          "accessToken": {
            "type": "string"
          },
          "tokenType": {
            "type": "string",
            "default": "Bearer"
          },
          "expiresIn": {
            "type": "integer",
            "format": "int64",
            "description": "Access token expiry in milliseconds"
          },
          "userId": {
            "type": "string",
            "format": "uuid"
          },
          "email": {
            "type": "string",
            "format": "email"
          },
          "refreshToken": {
            "type": "string"
          }
        }
      },
      "ApiResponseRegisterResponse": {
        "type": "object",
        "properties": {
          "timestamp": {
            "type": "string",
            "format": "date-time"
          },
          "status": {
            "type": "integer"
          },
          "message": {
            "type": "string"
          },
          "data": {
            "$ref": "#/components/schemas/RegisterResponse"
          }
        }
      },
      "ApiResponseLoginResponse": {
        "type": "object",
        "properties": {
          "timestamp": {
            "type": "string",
            "format": "date-time"
          },
          "status": {
            "type": "integer"
          },
          "message": {
            "type": "string"
          },
          "data": {
            "$ref": "#/components/schemas/LoginResponse"
          }
        }
      },
      "ErrorResponse": {
        "type": "object",
        "properties": {
          "timestamp": {
            "type": "string",
            "format": "date-time"
          },
          "status": {
            "type": "integer"
          },
          "errorCode": {
            "type": "string"
          },
          "message": {
            "type": "string"
          },
          "path": {
            "type": "string"
          },
          "errors": {
            "type": "object",
            "additionalProperties": {
              "type": "string"
            },
            "description": "Field-level validation errors (only present on 400 validation failures)"
          }
        }
      }
    }
  }
}
